cs/fsm.py
cs_fsm-20250120.dist-info/WHEEL
cs_fsm-20250120.dist-info/METADATA
cs_fsm-20250120.dist-info/RECORD
